yst_xhs/__init__.py
yst_xhs/main.py
yst_xhs/apis/__init__.py
yst_xhs/apis/pc_apis.py
yst_xhs/static/xhs_xray.js
yst_xhs/static/xhs_xray_pack1.js
yst_xhs/static/xhs_xray_pack2.js
yst_xhs/static/xhs_xs_xsc_56.js
yst_xhs/xhs_utils/__init__.py
yst_xhs/xhs_utils/common_utils.py
yst_xhs/xhs_utils/cookie_util.py
yst_xhs/xhs_utils/data_util.py
yst_xhs/xhs_utils/xhs_util.py
yst_xhs-0.1.3.dist-info/METADATA
yst_xhs-0.1.3.dist-info/WHEEL
yst_xhs-0.1.3.dist-info/entry_points.txt
yst_xhs-0.1.3.dist-info/top_level.txt
yst_xhs-0.1.3.dist-info/RECORD
