Metadata-Version: 2.4
Name: yst_xhs
Version: 0.1.3
Summary: 小红书爬虫工具
Author: yst
Author-email: 
Classifier: Programming Language :: Python :: 3
Classifier: License :: OSI Approved :: MIT License
Classifier: Operating System :: OS Independent
Requires-Python: >=3.6
Requires-Dist: PyExecJS
Requires-Dist: requests
Requires-Dist: loguru
Requires-Dist: python-dotenv
Requires-Dist: retry
Requires-Dist: openpyxl
Dynamic: author
Dynamic: classifier
Dynamic: requires-dist
Dynamic: requires-python
Dynamic: summary
